performanceplatform
tests
