Metadata-Version: 1.0
Name: performanceplatform-client
Version: 0.11.5
Summary: A client library for sending data to the Performance Platform
Home-page: https://github.com/alphagov/performanceplatform-client
Author: Government Digital Service
Author-email: performance@digital.cabinet-office.gov.uk
License: MIT
Keywords: api data performance_platform
Platform: UNKNOWN
